Workbook

Sheet Progress Table
A1: Problem Statement | B1: Objectives | C1: Scopes | D1: Features | E1: Platform | F1: Status | G1: Target Date of Completion | H1: Date of Completion | I1: Owner | J1: Remarks
A2: How can a blockchain-based, gamified Filipino culinary word-puzzle application support vocabulary and heritage learning while maintaining engagement through gamification and securing rewards through a transparent, tamper-resistant blockchain mechanism? | B2: Objective 1: Provide a module that will support culinary vocabulary and recipe-based learning and cultural awareness through interactive word puzzles. | C2: WORD PUZZLE GAME ENGINE | D2: Letter input validation | E2: Mobile | F2: OK | H2: 2026-08-10 | I2: Mau | J2: Rejects incomplete and non-alphabetic guesses at any word length. 10 unit tests.
D3: Color-coded feedback (correct / misplaced / absent) | E3: Mobile | F3: OK | H3: 2026-08-10 | I3: Mau | J3: Two-pass verdict algorithm. Fixed Capstone 1 defect D-01 where repeated letters produced phantom yellow tiles. A/D/X colour legend is tutorial-only, using the KUSINA KODE cream tile outline (2026-09-16).
D4: Variable-length word support (5, 6, 8+ letters) | E4: Mobile | F4: OK | H4: 2026-08-10 | I4: Mau | J4: End to end. Levels 21-27 seeded via migration 002. No fixed 6x6 grid remains.
D5: Attempt tracking and history logging | E5: Mobile | F5: OK | H5: 2026-08-10 | I5: Mau | J5: post_attempt.php records every guess with time_taken_ms (migration 001).
D6: Max-attempts scaling by word length | E6: Mobile | F6: Scope Change | I6: Mau | J6: NOT BUILT AS WRITTEN. Team decided 2026-08-10 on a flat 6 attempts for every dish. Amend this line or reinstate scaling before defense.
D7: Round resume after leaving the screen | E7: Mobile | F7: OK | H7: 2026-08-12 | I7: Mau | J7: SavedRound persisted per account. Defect D-10.
D8: Player onboarding and How to Play tutorial | E8: Mobile | F8: OK | H8: 2026-08-10 | I8: UNASSIGNED | J8: Built and working, but not named in any signed module. Ownership needs confirming. Pause menu (2026-09-06): live Sound FX slider (0–100%) also on Settings; persists and applies mid-round. Settings screen (2026-09-17): cream circle back, parchment cards, circular wells; version/ledger footer gone. Pause overlay (2026-09-16): Resume/leave actions are Compose HUD pills with Be Vietnam Pro ExtraBold; a matching well-width spacer keeps each label in the true center of the candy (D-42). In-game How to Play (2026-09-16): same parchment plate; compact terracotta OK with no check; Spend KK lists Reveal / Bomb / Solve as separate rows. Win bed (D-37) loops through the card pot and CORRECT! until Next Level or Back to Map. Dedicated looping beds (2026-09-06): Learn/KODEX, Wallet, Profile and Leaderboard. Story film (2026-09-16): last frame auto-advances — no tap-to-continue (D-39). Practice Skip sits above the chef overlay so it leaves immediately (D-40).
D9: Dish dataset schema (history, region, ingredients, procedure, tools, significance) | E9: Content / Backend | F9: OK | H9: 2026-08-25 | I9: Kyla | J9: Landed 2026-08-25 from KK-DISHES-INFO.xlsx. DishCatalog.kt holds all 30 dishes with origin story, ingredients, numbered steps, equipment, region, rating, cooking time and a source reference. Generated, not hand-typed, so the sheet stays the single source. Screens read from it - the hand-written sample write-ups and 'curation pending' shells are gone.
D10: Post-round reveal UI | E10: Mobile | F10: OK | H10: 2026-08-10 | I10: Kyla | J10: Win screen leads to the KODEX masterclass dish page with heritage card. Claim Card is a compact PlayNowBrown pill (2026-09-16); CORRECT! Next Level uses the same brown and no arrow. KODEX hub pantry grid (2026-09-03): Featured Ingredients opens All; Rare Ingredients opens the Rare tab. Hub DISHES stack (2026-09-06): only solved dishes; empty card keeps the locked cloche without the 'Solve a dish first' caption (2026-09-16). Palayok ritual (2026-09-06): open 1 after a win; leftovers wait in the pantry. Grant: 6 on first try down to 1 on the last guess; any power-up subtracts 2 (floor 1). KODEX pantry uses one palayok — CHOOSE 1 OR OPEN ALL — then a stacked haul deck (tap or swipe); NEW ingredients sit at the top of the shelf. Live XAMPP (D-44, 2026-09-16): pantry/ and report/ copied into REST so snapshot.php is no longer a 404. Pantry How it Works (2026-09-17): same parchment plate and compact terracotta OK as in-game How to Play. Palayok pick (2026-09-17): congratulations is LEVEL CLEAR game type with no SKIP — a pot has to be chosen; the chosen pot shakes about 3s then the ingredient stays on the spotlight 2s before the card (tap skips); sell confirms then trades through a large Chef's Vault (D-51); while TRADING the sold ingredients keep flying in from the sides and up from the pantry into the stall, then KK flows out. Masterclass header (2026-09-17): cream chrome back, heart and settings matching KODEX; Validated check is green and the toggle reads Sources. Pantry DRAW 1 (2026-09-17): the palayok shakes about 3s then holds the ingredient 2s before the card, same as the win ritual (D-52: pantry DRAW no longer flashes the pot in from the left). OPEN ALL (2026-09-17): the same shake, then every drawn ingredient rings the open palayok (It's opening…) before the haul cards; OPEN ALL and SEE PANTRY use Play Now brown. Baul overlay is a darker scrim.
D11: Regional coverage expansion (Mindanao: Maranao / Tausug dishes) | E11: Content | F11: OK | H11: 2026-08-25 | I11: Kyla | J11: Done 2026-08-25. Mindanao now has 5 researched levels (Tiyula Itum, Piaparan, Pastil, Sinuglaw, Satti) plus Kulma held in reserve - Maranao, Tausug and Maguindanao kitchens all represented. Spread is now Luzon 8 / Visayas 8 / Mindanao 5 / Philippines 6 instead of the old 17/7/3.
D12: Expert-validated recipe content (Chef Gicana) | E12: Content | F12: Not Started | I12: Kyla | J12: Content is now sourced and referenced per dish, but sourced is not endorsed: isValidated stays false and the KODEX still shows 'PREVIEW - expert validation in progress'. Chef Gicana's sign-off is what flips it.
D13: Dish content API endpoint | E13: Backend | F13: In Progress | I13: Kyla | J13: get_levels.php serves word and trivia. Full 6-field content endpoint outstanding. Levels table realigned to the dataset by migration 009 (27 rows, ids kept 1-27 so attempts and unlocks keep their foreign keys). api/lib/islands.php regenerated to match. The phone still reads levels locally - the endpoint serving the full 6-field content is what is outstanding.
D14: Points calculation on round completion | E14: Mobile | F14: OK | H14: 2026-08-10 | I14: Alyssa | J14: Base + unused attempts + speed tier + perfect bonus. 7 unit tests. Consistent across sessions and devices.
D15: Badge eligibility (round count, streak, perfect score) | E15: Mobile | F15: OK | H15: 2026-08-10 | I15: Alyssa | J15: Fires exactly on the threshold and never twice. 8 unit tests plus a DB unique key.
D16: Leaderboard ranking by accumulated points | E16: Mobile | F16: OK | H16: 2026-08-10 | I16: Alyssa | J16: Tie-broken by dishes solved then name. 7 unit tests. Kusina Masters (2026-09-17): cream circle back like Profile; trophy above first place removed. Board chrome (2026-09-17): gold/silver/bronze podium blocks, parchment rank rows, terracotta period pills.
D17: Progress tracking view (attempt history) | E17: Mobile | F17: OK | H17: 2026-08-10 | I17: Mau | J17: Totals, streaks, badges and recent attempts on the Progress screen. Profile Digital Badges (2026-09-17): locked slots keep the icon and lock only — names show after the badge is earned. Edit opens the trophy case (earned and still-to-earn), not See all.
D18: Blockchain-verification status UI (pending / confirmed) | E18: Mobile | F18: OK | H18: 2026-08-10 | I18: Alyssa | J18: Stub as the brief requires. Driven by Badge.tx_hash; markBadgeConfirmed() deliberately caller-less until Module 3.
D19: Power-ups purchasable with KKCoin | E19: Mobile | F19: OK | H19: 2026-08-24 | I19: Alyssa | J19: Reveal 5 KK and Bomb 10 KK both allowed per dish with a 1-minute cooldown between them. Instant Solve is live at 50 KK so it stays rare. XP/points never buy help. POST reward/spend.php prices are server-fixed.
D20: Phase 1: event trigger + AES-256 encrypt + SHA-256 hash | E20: Backend / Chain | F20: OK | H20: 2026-08-20 | I20: Alyssa | J20: Live on XAMPP 2026-08-20: POST /kusinakode/REST/reward/trigger.php returned phase=1 status=pending payload_hash (64 hex) signature=null tx_hash=null. AES-256-GCM then SHA-256 of ciphertext. Pipeline is in api/lib/ + reward/. 12 Phase 1 unit tests PASS.
D21: Phase 2: transaction assembly + ECDSA sign + PoA validation | E21: Backend / Chain | F21: OK | H21: 2026-08-20 | I21: Alyssa | J21: Private Polygon-compatible sidechain with Proof-of-Authority (not public mainnet). Live 2026-08-20: GET reward/status.php advanced tx_ref kk_afa18649… to phase=2 pending with ECDSA signature. Implemented as local PHP PoA on XAMPP — not a public Polygon node yet. PoA unit tests PASS.
D22: Phase 3: block append + chain sync | E22: Backend / Chain | F22: OK | H22: 2026-08-20 | I22: Alyssa | J22: Tamper-evident linking across validator nodes. Live 2026-08-20: same tx_ref advanced to phase=3 pending with block_ref 8a09a18d…. One local chain (api/chain/data) on XAMPP, not multiple Azure validator VMs (Kyla). Chain append + genesis sync unit tests PASS.
D23: Phase 4: smart contract execution + TxHash receipt | E23: Backend / Chain | F23: OK | H23: 2026-08-20 | I23: Alyssa | J23: Smart contract must transfer tokens / mint badge and return a TxHash. Live 2026-08-21: round_win tx_hash 0xe163f183… amount_kk=10. Live 2026-08-24: badge_milestone tx_ref kk_f5236886… phase=4 confirmed tx_hash 0xae5021b2… amount_kk=25; badges.tx_hash pointer set. Azure node is Kyla.
D24: Reward token contract (ERC-20-style) | E24: Backend / Chain | F24: OK | H24: 2026-08-21 | I24: Alyssa | J24: Design choice, not a literal manuscript requirement — confirm with adviser. KKCoin.sol validator-only mintFromPool. Live 2026-08-21: balance_kk=10; live 2026-08-24 after badge mint balance_kk=35 at 0xcb2e9f…. Hardhat suite green 2026-08-25 on Windows/Node 24: npx hardhat test = 5 passing. Config fix: paths.sources was '.' so Hardhat scanned node_modules and failed HH1006 on any machine; sources moved to contracts/src/.
D25: Badge/achievement contract (ERC-721-style) | E25: Backend / Chain | F25: OK | H25: 2026-08-24 | I25: Alyssa | J25: Same design-decision caveat as the token contract. Live 2026-08-24: POST post_badge.php badge_id live-mint-20260824 then status polls reached phase=4 tx_hash 0xae5021b2…. Duplicate POST returned awarded=false tx_ref=null. Chain state has one mint at 0xcb2e9f…|live-mint-20260824. Hardhat suite green 2026-08-25: 5 passing, including the duplicate-mint rejection.
... D31: Mobile wallet and reward UI (balance, verifying → verified, TxHash) | E31: Mobile | F31: OK | H31: 2026-08-24 | I31: Alyssa | J31: Player-facing display only. +10 KK per new dish (replay +0). Badge +25 is claimed on Rewards. Island +15 KK (2026-09-17): CLAIM then CLAIMED on How to Earn — not auto-minted — and a system + inbox notice. Shops: Kusina Reel, KODEX Pantry, Chef's Atelier portrait frames. Kusina Reel restyled 2026-09-03 to match the Rewards header (cream circle back button, KK coin instead of the letters KK) and a 2-by-2 grid of dish-photo posters from REELS-DISHES.zip — 30 dish reels. Recent History lists the caller's TxHash receipts from GET reward/history.php.
D32: User CRUD and search | E32: Web | F32: In Progress | I32: Yow | J32: ASP.NET Web Forms CRUD exists from Capstone 1. Search and Capstone 2 refresh outstanding.
D33: Dish/content CRUD (all 6 cultural fields) | E33: Web | F33: In Progress | I33: Yow | J33: Blocked on the validated dataset.
D34: Blockchain audit panel (log + transaction detail) | E34: Web | F34: Not Started | I34: Yow | J34: Backend live-checked 2026-08-24 (admin 200, player 403). Dashboard UI still outstanding.
D35: Role-based access enforcement (Player vs Admin) | E35: Web | F35: In Progress | I35: Yow | J35: Backend ready: users.role (migration 004) and kk_require_admin(). Dashboard enforcement outstanding.
D36: Login and sign-up (mobile) | E36: Mobile | F36: OK | H36: 2026-08-10 | I36: UNASSIGNED | J36: Built and working but not named in any signed module. Ownership needs confirming. Profile (2026-09-17): extra space under the handle before the stat tiles; the pencil opens a ledger-ticket overlay instead of an inline editor; email and Sign Out live only on Settings. Continue Learning (2026-09-17): full region taglines on Profile and Home; tapping Luzon/Visayas/Mindanao/Philippines opens that island map, See all opens All. Settings (2026-09-17): cream HeaderCircleButton back like Progress; parchment cards with circular icon wells; version and custodial-wallet footer removed. Chain (2026-09-17): register.php and login.php write 0 KK account_signup / account_login receipts through the same four-phase pipeline as rewards. Passwords and emails never go on-chain. Sign-up appears in On-Chain Activity; logins stay on the admin audit log so the inbox is not a session dump.
D37: Bearer-token session and per-account authorisation | E37: Backend | F37: OK | H37: 2026-08-12 | I37: Alyssa | J37: Identity derived from the credential, never a user_id in the request. Defect D-14. 12 API checks.
D38: Password reset with expiring OTP | E38: Backend | F38: OK | H38: 2026-08-17 | I38: Alyssa | J38: Reset code no longer returned in the API response (critical defect D-20). Requires SMTP to be usable off localhost.
D39: Brute-force throttling and account lockout | E39: Backend | F39: OK | H39: 2026-09-02 | I39: Alyssa | J39: Login lockout is per email/username only (8 fails / 15 min). Same-IP accounts stay independent. Register reset and reward still count identifier or IP. Defect D-21 then D-33.
D40: Server-side session revocation on sign-out | E40: Backend + Mobile | F40: OK | H40: 2026-08-17 | I40: Alyssa | J40: logout.php revokes the calling token or all sessions. Defect D-25.
D41: Azure AD B2C authentication and RBAC | E41: Cloud | F41: Not Started | I41: Kyla + Alyssa | J41: Interim tokens are B2C-shaped so only auth.php changes.
D42: Azure VM (PHP REST API + blockchain node) | E42: Cloud | F42: Not Started | I42: Kyla
D43: Azure App Service (admin dashboard hosting) | E43: Cloud | F43: Not Started | I43: Kyla
D44: Azure SQL Database (relational data) | E44: Cloud | F44: Not Started | I44: Kyla
D45: Azure Cosmos DB (dish/recipe content) | E45: Cloud | F45: Not Started | I45: Kyla
D46: Azure Blob Storage (images) | E46: Cloud | F46: Not Started | I46: Kyla
D47: Azure Key Vault (secrets) | E47: Cloud | F47: Not Started | I47: Kyla | J47: Seam built: config.php reads every secret from the environment with a local fallback, so no code changes to deploy.
D48: HTTPS/TLS transport | E48: Cloud | F48: Not Started | I48: Mau | J48: HIGH PRIORITY. Traffic is currently plaintext HTTP, so passwords and tokens are readable on the network.
D49: Replace hard-coded LAN endpoint with the Azure host | E49: Mobile + Cloud | F49: Not Started | I49: Mau | J49: Defect D-19. App cannot reach the server after any network change.
D50: Unit tests per module (5-module breakdown) | E50: Both | F50: In Progress | H50: 2026-08-17 | I50: Yow | J50: Modules 1 and 2 fully covered: 82 tests, 0 failures. Module 3 PHP runner 51 passed 0 failed on 2026-08-24. Modules 4 and 5 pending those modules.
D51: Stress testing (API, DB, blockchain node, mobile rendering) | E51: Both | F51: Not Started | I51: Yow | J51: 3 of 4 targets blocked. Mobile rendering is NOT blocked and can run today.
D52: Manuscript-claim-vs-build tracking | E52: Both | F52: OK | H52: 2026-08-17 | I52: Kyla | J52: docs/testing/ holds a rebuildable log: unit results parsed from JUnit XML, API checks, defect log, known gaps.
D53: Clean Architecture layering for the web admin | E53: Web | F53: In Progress | H53: 2026-08-17 | I53: Yow | J53: KusinaKode.Domain assembly (netstandard2.0, zero dependencies) with 20 unit tests; repository interfaces; AdminDashboardService; presentation ViewModel. MVVM is not possible in Web Forms — this is Clean Architecture plus a Presentation Model.
D54: Story Mode - origin story of Kusina Kode (Filipino pixel-art) | E54: Mobile | F54: OK | H54: 2026-08-25 | I54: Mau | J54: Built 2026-08-25 (Mau). 5 chapters, hand-authored pixel sprites drawn in Compose (ui/story/PixelArt.kt) - no bitmap assets, scales to any density. Skippable. Verified on emulator. Runs after onboarding and replayable from How to Play. Plays automatically on signup only; login goes straight to the dashboard and the story is replayable from Home > Story & Guides.
D55: Tutorial Mode - scripted playable walkthrough on the real game UI | E55: Mobile | F55: OK | H55: 2026-08-25 | I55: Mau | J55: Built 2026-08-25 (Mau). ui/tutorial/TutorialGameScreen.kt uses the real GameTile, CustomKeyboard and WordleEngine on a fixed ADOBO board - not a mock-up. Not scored, nothing pushed to the server. Coaching line reacts to the player's actual guesses. Verified end-to-end on emulator.
D56: Interactive onboarding walkthrough (coach-mark overlays) | E56: Mobile | F56: OK | H56: 2026-08-25 | I56: Mau | J56: Built 2026-08-25 (Mau). ui/onboarding/CoachMarks.kt: spotlight overlay with BlendMode.Clear cutout, anchors registered via Modifier.coachAnchor. 4 steps on Home covering clue-to-puzzle, streak counter, on-chain badges and leaderboard tier - the three the panel named. Per-user flag so a second account is shown around too.
D57: How It Works help module on the game dashboard | E57: Mobile | F57: OK | H57: 2026-08-25 | I57: Mau | J57: Built 2026-08-25 (Mau). Panel's 3 steps added to the top of HowToPlayContent, so they appear in both existing entry points (InstructionScreen and the in-game help dialog). Step 3 now says the badge is minted automatically, matching the new behaviour.
D58: KKCoin tutorial - how to earn and spend KK | E58: Mobile | F58: OK | H58: 2026-08-25 | I58: Mau | J58: Built 2026-08-25 (Mau). ui/tutorial/KkTutorialScreen.kt closes the intro chain. Amounts read from the same PowerUp constants the game uses so the page cannot drift from the economy. Verified on emulator.
D59: Avatar marketplace enhancement (Chef's Atelier) | E59: Mobile | F59: OK | H59: 2026-08-25 | I59: Mau | J59: Rebuilt 2026-08-25 (Mau). Locked chefs and frames are shown on their own — they do not preview as a pair until unlocked. Tapping a locked look opens the Add to your Kusina? dialog; owned looks wear on tap. Tiles are flat (no selected shadow). House Cook sits on the same cream plate as shop busts. Chef subtitles name the person (role), not the outfit. Frame subtitles name the wreath or ornament. 2026-09-03: live shop.php now prices avc_* chefs (D-34); confirm button says Buy. Buy (2026-09-16) wears the same terracotta candy as pause Resume.
D60: Notifications - claimable reward, badge earned, streak reminder | E60: Mobile | F60: In Progress | I60: Mau | J60: Built 2026-08-25 (Mau): KusinaNotifications with Rewards and Reminders channels, POST_NOTIFICATIONS runtime request, a notification when a badge finishes minting, and a daily-claim nudge on app open. NOT DONE: reminders while the app is closed (streak nudge, end-of-day daily warning) - those need WorkManager, which was deliberately not added. Verified permission prompt on emulator. In-app Notifications screen added behind the Home header bell - claimable rewards plus every on-chain reward with its TxHash, since system notifications vanish once dismissed. Bell count (D-41, 2026-09-16): daily claim is two waiting rows (KK + palayok), so the badge matches WAITING FOR YOU. Inbox (2026-09-16): minted title drops the bang and status is title-cased (Confirmed); Mark all read / Select / Archived sit on the right. On-chain list is newest-first (2026-09-17). Ledger ticket (D-43): report is a button, details are required, Done hides while filing. Junk like aaa is rejected (D-45: 12+ characters in the player's own words). Daily inbox title is Daily 2026-09-17; Recorded converts UTC to the phone's local time. Island complete (2026-09-17, D-46): CLAIMED chip plus waiting/claimed notifications, same as Daily Login. Palayok free spin (D-47, 2026-09-17): daily claim banks the spin; a claimed day missing one is repaired on the next pantry snapshot. Inbox (D-48, 2026-09-17): resume refreshes so a claimed daily moves to On-Chain Activity; Daily palayok spin stays in Waiting until the wheel is turned. After the wheel (D-49, 2026-09-17): pantry/spin.php writes a palayok_spin receipt (0 KK) so On-Chain Activity lists Daily login claim then Daily palayok spin. Waiting titles match those two names. Inbox chrome (2026-09-17): parchment cards matching Settings, one box per row, no circular wells. Empty inbox (2026-10-11): a tab with nothing to claim or show uses the same centered message as KK Transaction, with the brown bell and no note card.
D61: Remove SOON placeholder labels now that KK is live | E61: Mobile | F61: OK | H61: 2026-08-25 | I61: Mau | J61: Done 2026-08-25 (Mau). UtilityCard default badge is now OPEN and the SOON styling branch is gone; the win-screen reward stack is KK and badges only. KODEX UNLOCKED then UNLOCK FOOD DOCUMENTARY sit below the stack
D62: Auto-mint badges on victory (remove the manual claim step) | E62: Mobile / Backend | F62: OK | H62: 2026-08-25 | I62: Alyssa | J62: Built 2026-08-25. ChainRewardCoordinator subscribes to GamificationEvents.badgesEarned - the seam the gamification module already announced badges on for this purpose - and runs claim + settle immediately. Manual CLAIM on Rewards still works for the daily. NOTE: this lands in Alyssa's module; she was mid-change on badge claiming, so it needs her review before merge.
D63: Transparent cryptographic status indicators (on-chain progress feedback) | E63: Mobile | F63: OK | H63: 2026-08-25 | I63: Alyssa | J63: Built 2026-08-25. domain/ChainEvents.kt carries pipeline state; ui/components/ChainStatusBanner.kt is hosted at the navigation root so a mint that starts in a round is still visible after the player moves on. Shows 'Validating ... on-chain', then the mint with its TxHash; tapping copies the hash (the 'View TxHash Proof' affordance).
D64: Downloadable badge certificate (PDF) on claim | E64: Mobile | F64: Scope Change | I64: Alyssa | J64: Built 2026-08-25 then REMOVED the same day at the team's request. The PDF generator, the on-screen certificate, the badge tap target and the FileProvider that shared the file are all gone; badges are display-only again. Nothing else depended on it. Re-add it here as Not Started if the decision is revisited - the TxHash it printed is still on every confirmed badge.
D65: Palayok open one or all | E65: Mobile | F65: In Progress | I65: Alyssa | J65: A single waiting palayok offers Draw 1 only. Open all appears when two or more are waiting. When the pot opens it stays in the middle, and the ingredient rises out of it and floats just above. Checked on the emulator.
D66: Shelf ingredient trading card | E66: Mobile | F66: In Progress | I66: Alyssa | J66: Tapping an ingredient already on the shelf opens the collectible card, the same size as the palayok card. The category, such as Vegetable, is one brown with a light edge so it stays readable on every frame, including Legendary, and it sits above the description. The quantity, such as 1 ON THE SHELF, is near-black on pale cards and light on the blue card. A palayok reveal still says INGREDIENT UNLOCKED and SHELVED IN YOUR PANTRY. The name banner shrinks until the full title fits, including a closing parenthesis. Checked on the emulator.
D67: Pantry duplicate sell quantity | E67: Mobile | F67: In Progress | I67: Alyssa | J67: KODEX Pantry Sell on a stack of 2 or more opens a chooser from 1 to the owned count, shows the KK for that count, and sells only the chosen number. The chooser is a terracotta slider with minus on the left and plus on the right, on the same parchment card. A single copy still confirms a sale of 1. The older pantry shelf uses the same chooser. Unit-tested the count clamp. Alyssa checked the chooser on the emulator: terracotta track and knob, and small Sell-style minus and plus with no bottom shadow.
D68: Leaderboard shows your own rank | E68: Mobile / Backend | F68: OK | H68: 2026-10-12 | I68: Mau | J68: Kusina Masters lists the top 50. The player's own row is brown with a YOU chip; outside the top 50 it stays pinned under the list with the real rank (get_leaderboard.php?me= returns it, using the board's own ordering). Inside the top 50 it pins to the bottom until scrolled to, then to the top once scrolled past. The header and podium no longer scroll. Older app versions get the same reply as before. Unit-tested in LeaderboardViewModelTest; checked on the emulator at rank #39 and #32.
D69: Painted Luzon and Mindanao level maps | E69: Mobile | F69: In Progress | I69: Alyssa | J69: Luzon and Mindanao use their painted flag maps inside the same card, with sea above the island. A solved flag is the dish, the level still to solve shows the brown play button, and a locked flag keeps the question mark. Luzon flag 15 and Mindanao flag 7 say Coming soon. The chef stands on the current flag and walks to the next after a level is solved. Back to Map opens that level's island. The whole chart uses the new Philippines picture.
D70: Painted Visayas level map | E70: Mobile | F70: In Progress | I70: Alyssa | J70: Visayas uses the same painted flag map as Luzon and Mindanao, inside the same card, with sea above the island. A solved flag is the dish, the level still to solve shows the brown play button in the middle of the shield, and a locked flag keeps the question mark. Flags past the dishes say Coming soon. The chef on level 1 rests to the left of the flag so he stays visible, and he walks to the next flag after a level is solved.
D71: KODEX recent pot shelf | E71: Mobile | F71: In Progress | I71: Alyssa | J71: KODEX pantry shows up to three floating shelf cards. They are the ingredients most recently drawn from the pot, and if fewer than three were drawn the row fills the rest with other ingredients the player already owns. There is no Sell button and no KK amount. The count is a bold number and then gray on the shelf. A long name ends in an ellipsis. Tapping a card opens the collectible. The category stays the same brown, with a light edge on every card, including the purple Legendary panel. Checked on the emulator.
D72: Pause menu label seat | E72: Mobile | F72: In Progress | I72: Alyssa | J72: Keep Playing and Leave Round sit in the middle of the candy, a little to the right and a little down. The icon well stays on the left. The same seat is used by the other pause buttons that share this candy. Checked on the emulator.

Sheet Progress
A1: Kusina Kode - Feature Completion Tracker
A2: Per-module readiness. Figures are formulas over the Progress Table tab.
A4: Total Features | B4: Done | C4: In Progress | D4: Not Started | E4: Needs Decision | F4: Overall %
A6: =COUNTA('Progress Table'!$F$2:$F$72) | B6: =COUNTIF('Progress Table'!$F$2:$F$72,"OK") | C6: =COUNTIF('Progress Table'!$F$2:$F$72,"In Progress") | D6: =COUNTIF('Progress Table'!$F$2:$F$72,"Not Started") | E6: =COUNTIF('Progress Table'!$F$2:$F$72,"Scope Change") | F6: =IFERROR(B6/A6,0)
A8: # | B8: Module | C8: Total Features | D8: Done | E8: % Complete | F8: Status
A9: 1 | B9: WORD PUZZLE GAME ENGINE | C9: =COUNTA('Progress Table'!$F$2:$F$72) | D9: =COUNTIF('Progress Table'!$F$2:$F$72,"OK") | E9: =IFERROR(D9/C9,0) | F9: =IF(E9=1,"Complete",IF(E9>0,"In Progress","Not Started"))
A10: 2 | B10: CULTURAL CONTENT | C10: =COUNTA('Progress Table'!$F$9:$F$70) | D10: =COUNTIF('Progress Table'!$F$9:$F$70,"OK") | E10: =IFERROR(D10/C10,0) | F10: =IF(E10=1,"Complete",IF(E10>0,"In Progress","Not Started"))
A11: 3 | B11: GAMIFICATION | C11: =COUNTA('Progress Table'!$F$14:$F$71) | D11: =COUNTIF('Progress Table'!$F$14:$F$71,"OK") | E11: =IFERROR(D11/C11,0) | F11: =IF(E11=1,"Complete",IF(E11>0,"In Progress","Not Started"))
A12: 4 | B12: BLOCKCHAIN INCENTIVE | C12: =COUNTA('Progress Table'!$F$20:$F$64) | D12: =COUNTIF('Progress Table'!$F$20:$F$64,"OK") | E12: =IFERROR(D12/C12,0) | F12: =IF(E12=1,"Complete",IF(E12>0,"In Progress","Not Started"))
A13: 5 | B13: ADMINISTRATIVE DASHBOARD | C13: =COUNTA('Progress Table'!$F$32:$F$53) | D13: =COUNTIF('Progress Table'!$F$32:$F$53,"OK") | E13: =IFERROR(D13/C13,0) | F13: =IF(E13=1,"Complete",IF(E13>0,"In Progress","Not Started"))
A14: 6 | B14: AUTHENTICATION AND IDENTITY | C14: =COUNTA('Progress Table'!$F$36:$F$41) | D14: =COUNTIF('Progress Table'!$F$36:$F$41,"OK") | E14: =IFERROR(D14/C14,0) | F14: =IF(E14=1,"Complete",IF(E14>0,"In Progress","Not Started"))
A15: 7 | B15: CLOUD INFRASTRUCTURE AND SECURITY | C15: =COUNTA('Progress Table'!$F$42:$F$49) | D15: =COUNTIF('Progress Table'!$F$42:$F$49,"OK") | E15: =IFERROR(D15/C15,0) | F15: =IF(E15=1,"Complete",IF(E15>0,"In Progress","Not Started"))
A16: 8 | B16: TESTING, QA AND DOCUMENTATION | C16: =COUNTA('Progress Table'!$F$50:$F$52) | D16: =COUNTIF('Progress Table'!$F$50:$F$52,"OK") | E16: =IFERROR(D16/C16,0) | F16: =IF(E16=1,"Complete",IF(E16>0,"In Progress","Not Started"))
B17: TOTAL | C17: =SUM(C9:C16) | D17: =SUM(D9:D16) | E17: =IFERROR(D17/C17,0)
A19: Status legend: OK = built and verified · In Progress = started, incomplete · Not Started = no work yet · Scope Change = built differently from the written feature, needs a team decision.

Sheet Integration and Unit
A1: Test No. | B1: Test Case | C1: Remarks (Pass/Fail) | E1: Test No. | F1: Test Case | G1: Description of Test Case | H1: Remarks (Pass/Fail)
A2: U-001 | B2: AchievementBadgeTest: a loss earns no achievement | C2: Pass | E2: I-001 | F2: Unauthenticated write is rejected | G2: POST post_progress.php | input: no token, body {"user_id":1,"total_points":999999} | expected: 401 | actual: 401 | H2: Pass
A3: U-002 | B3: AchievementBadgeTest: a one-guess win is not sea of green | C3: Pass | E3: I-002 | F3: Unauthenticated read is rejected | G3: GET get_progress.php | input: no token, ?user_id=1 | expected: 401 | actual: 401 | H3: Pass
A4: U-003 | B4: AchievementBadgeTest: a retired region in an old save does not count toward world explorer | C4: Pass | E4: I-003 | F4: Unauthenticated read is rejected | G4: GET get_badges.php | input: no token | expected: 401 | actual: 401 | H4: Pass
A5: U-004 | B5: AchievementBadgeTest: a yellow tile anywhere rules out sea of green | C5: Pass | E5: I-004 | F5: Unauthenticated read is rejected | G5: GET get_attempts.php | input: no token | expected: 401 | actual: 401 | H5: Pass
A6: U-005 | B6: AchievementBadgeTest: a zero duration does not count as fast | C6: Pass | E6: I-005 | F6: Unauthenticated write is rejected | G6: POST post_badge.php | input: no token | expected: 401 | actual: 401 | H6: Pass
A7: U-006 | B7: AchievementBadgeTest: achievements are awarded once | C7: Pass | E7: I-006 | F7: Unauthenticated write is rejected | G7: POST update_profile.php | input: no token | expected: 401 | actual: 401 | H7: Pass
A8: U-007 | B8: AchievementBadgeTest: clean kitchen needs zero power-ups | C8: Pass | E8: I-007 | F8: Forged token is rejected | G8: GET get_badges.php | input: Authorization: Bearer deadbeef | expected: 401 | actual: 401 | H8: Pass
A9: U-008 | B9: AchievementBadgeTest: fast thinker is under the threshold | C9: Pass | E9: I-008 | F9: Bad credentials give no token | G9: POST login.php | input: unknown email and wrong password | expected: error, no token | actual: error, no token | H9: Pass
A10: U-009 | B10: AchievementBadgeTest: instant solve cannot buy sea of green | C10: Pass | E10: I-009 | F10: Register issues a token | G10: POST register.php | input: new account authtest_a | expected: 64-char hex token | actual: 64-char hex token | H10: Pass
A11: U-010 | B11: AchievementBadgeTest: instant solve does not count as a last plating | C11: Pass | E11: I-010 | F11: Authenticated write succeeds | G11: POST post_progress.php | input: valid token, 250 points | expected: success | actual: success | H11: Pass
A12: U-011 | B12: AchievementBadgeTest: knowledge badges count distinct dishes read | C12: Pass | E12: I-011 | F12: Spoofed user_id in body is ignored | G12: POST post_progress.php | input: token = user 49, body user_id 50, 888888 pts | expected: writes to row 49 | actual: row 49 = 888888 and row 50 absent | H12: Pass
... A47: U-046 | B47: ErrorMappingTest: a timeout reads as the server not answering, not as being offline | C47: Pass | E47: I-046 | F47: Unauthenticated report submit is rejected | G47: POST report/submit.php | input: no token | expected: 401 JSON | actual: 401 Authentication required | H47: Pass
A48: U-047 | B48: ErrorMappingTest: an unrecognised failure still produces something calm and retryable | C48: Pass
A49: U-048 | B49: ErrorMappingTest: an unresolvable host reads as offline | C49: Pass
A50: U-049 | B50: ErrorMappingTest: mapNetworkError wraps a failure once, not repeatedly | C50: Pass
A51: U-050 | B51: ErrorMappingTest: no message ever leaks a raw url into the headline | C51: Pass
A52: U-051 | B52: ExampleUnitTest: addition_isCorrect | C52: Pass
A53: U-052 | B53: FeaturedBadgesTest: a chosen badge that is not earned is dropped, not shown as locked | C53: Pass
A54: U-053 | B54: FeaturedBadgesTest: a chosen showcase is shown in the player's order | C54: Pass
A55: U-054 | B55: FeaturedBadgesTest: a new player with nothing earned still sees locked slots to aim at | C55: Pass
A56: U-055 | B56: FeaturedBadgesTest: a partial choice is topped up rather than leaving gaps | C56: Pass
A57: U-056 | B57: FeaturedBadgesTest: a short roster does not pad beyond what exists | C57: Pass
A58: U-057 | B58: FeaturedBadgesTest: more choices than slots are trimmed to the first ones | C58: Pass
A59: U-058 | B59: FeaturedBadgesTest: no choice falls back to earned badges first | C59: Pass
... A199: U-198 | B199: WordleEngineTest: repeated guess letter is not flagged more times than it appears in answer | C199: Pass
